alicelue_brocker_wihtoutapi/__init__.py
alicelue_brocker_wihtoutapi/alice.py
fyers_withoutapi/__init__.py
fyers_withoutapi/fyers.py
zerodha_without_api/__init__.py
zerodha_without_api/zerodha.py
zerodha_without_api-0.0.1.dist-info/LICENSE
zerodha_without_api-0.0.1.dist-info/METADATA
zerodha_without_api-0.0.1.dist-info/WHEEL
zerodha_without_api-0.0.1.dist-info/top_level.txt
zerodha_without_api-0.0.1.dist-info/RECORD
